{
  "schemaVersion": 1,
  "updatedAt": "2026-07-21",
  "terminology": {
    "internal2014": "2014",
    "public2014": "5e",
    "internal2024": "2024",
    "public2024": "5.5e",
    "note": "D&D Beyond changed labels on 2026-03-02. This was a terminology change only; internal values remain stable for saved-data compatibility."
  },
  "statusDefinitions": {
    "verified": "Checked against the cited primary source and protected by a test or exact-data comparison.",
    "verified-with-heuristic": "Official data is verified, but a clearly labeled DM Forge heuristic is also present.",
    "homebrew": "Original or user-created content; it must never be represented as official rules.",
    "names-only": "The interface lists a rule name but intentionally directs the DM to official text for adjudication.",
    "in-progress": "Source review is underway and the record must not be advertised as fully verified.",
    "needs-correction": "A known omission or mismatch exists and should be fixed before production claims are made."
  },
  "sources": {
    "dndbeyond-terminology-2026": {
      "title": "D&D Beyond Changelog — Updating 2024 to 5.5e",
      "url": "https://www.dndbeyond.com/changelog/",
      "publisher": "D&D Beyond / Wizards of the Coast"
    },
    "basic-2014-classes": {
      "title": "Basic Rules (2014) — Classes: Cleric",
      "url": "https://www.dndbeyond.com/sources/dnd/basic-rules-2014/classes",
      "publisher": "D&D Beyond / Wizards of the Coast"
    },
    "basic-2014-spells": {
      "title": "Basic Rules (2014) — Spells",
      "url": "https://www.dndbeyond.com/sources/dnd/basic-rules-2014/spells",
      "publisher": "D&D Beyond / Wizards of the Coast"
    },
    "basic-2014-combat": {
      "title": "Basic Rules (2014) — Combat",
      "url": "https://www.dndbeyond.com/sources/dnd/basic-rules-2014/combat",
      "publisher": "D&D Beyond / Wizards of the Coast"
    },
    "basic-2014-conditions": {
      "title": "Basic Rules (2014) — Appendix A: Conditions",
      "url": "https://www.dndbeyond.com/sources/dnd/basic-rules-2014/appendix-a-conditions",
      "publisher": "D&D Beyond / Wizards of the Coast"
    },
    "basic-2014-magic-items": {
      "title": "Basic Rules (2014) — Magic Items",
      "url": "https://www.dndbeyond.com/sources/dnd/basic-rules-2014/magic-items",
      "publisher": "D&D Beyond / Wizards of the Coast"
    },
    "free-2024-cleric": {
      "title": "Free Rules (2024) — Cleric",
      "url": "https://www.dndbeyond.com/sources/dnd/br-2024/character-classes-cleric",
      "publisher": "D&D Beyond / Wizards of the Coast"
    },
    "free-2024-spells": {
      "title": "Free Rules (2024) — Spell Descriptions",
      "url": "https://www.dndbeyond.com/sources/dnd/br-2024/spell-descriptions",
      "publisher": "D&D Beyond / Wizards of the Coast"
    },
    "free-2024-playing": {
      "title": "Free Rules (2024) — Playing the Game",
      "url": "https://www.dndbeyond.com/sources/dnd/br-2024/playing-the-game",
      "publisher": "D&D Beyond / Wizards of the Coast"
    },
    "free-2024-glossary": {
      "title": "Free Rules (2024) — Rules Glossary",
      "url": "https://www.dndbeyond.com/sources/dnd/br-2024/rules-glossary",
      "publisher": "D&D Beyond / Wizards of the Coast"
    },
    "free-2024-magic-items": {
      "title": "Free Rules (2024) — Magic Items A–Z",
      "url": "https://www.dndbeyond.com/sources/dnd/br-2024/magic-items-a-z",
      "publisher": "D&D Beyond / Wizards of the Coast"
    },
    "basic-2014-encounters": {
      "title": "Basic Rules (2014) — Building Combat Encounters",
      "url": "https://www.dndbeyond.com/sources/dnd/basic-rules-2014/building-combat-encounters",
      "publisher": "D&D Beyond / Wizards of the Coast"
    },
    "free-2024-encounters": {
      "title": "Free Rules (2024) — DM's Toolbox",
      "url": "https://www.dndbeyond.com/sources/dnd/br-2024/dms-toolbox",
      "publisher": "D&D Beyond / Wizards of the Coast"
    },
    "basic-2014-monsters": {
      "title": "Basic Rules (2014) — Monsters",
      "url": "https://www.dndbeyond.com/sources/dnd/basic-rules-2014/monsters",
      "publisher": "D&D Beyond / Wizards of the Coast"
    },
    "free-2024-monsters": {
      "title": "Free Rules (2024) — How to Use a Monster",
      "url": "https://www.dndbeyond.com/sources/dnd/br-2024/how-to-use-a-monster",
      "publisher": "D&D Beyond / Wizards of the Coast"
    },
    "srd-5-1": {
      "title": "Systems Reference Document 5.1",
      "url": "https://www.dndbeyond.com/srd",
      "publisher": "Wizards of the Coast",
      "license": "CC-BY-4.0"
    },
    "srd-5-2-1": {
      "title": "Systems Reference Document 5.2.1",
      "url": "https://www.dndbeyond.com/srd",
      "publisher": "Wizards of the Coast",
      "license": "CC-BY-4.0"
    }
  },
  "components": [
    {
      "id": "encounter-math",
      "repository": "cbw29512/monstercardforge",
      "path": "encounter-rules.js",
      "status": "verified-with-heuristic",
      "verifiedAt": "2026-07-21",
      "sourceIds": ["basic-2014-encounters", "free-2024-encounters", "basic-2014-monsters", "free-2024-monsters", "dndbeyond-terminology-2026"],
      "notes": [
        "Official 5e thresholds and multiple-monster multipliers are exact.",
        "Official 5.5e Low, Moderate, and High XP budgets are exact.",
        "CR 0 explicitly supports 0 or 10 XP; explicit zero values are preserved.",
        "Mixed-party average-level cautions and CR-spread review prompts are labeled DM Forge heuristics.",
        "5.5e encounters above the High budget are labeled Above High and receive a warning."
      ]
    },
    {
      "id": "cleric-slot-progression",
      "repository": "cbw29512/healingbox",
      "path": "rules-data.js#SLOTS",
      "status": "verified",
      "verifiedAt": "2026-07-21",
      "sourceIds": ["basic-2014-classes", "free-2024-cleric"],
      "notes": ["The full-caster slot progression used by the artifact is shared by the supported 5e and 5.5e Cleric tables. Legacy migration imports this same table rather than duplicating it."]
    },
    {
      "id": "cleric-spell-lists",
      "repository": "cbw29512/healingbox",
      "path": "rules-data.js#SPELLS",
      "status": "verified",
      "verifiedAt": "2026-07-21",
      "sourceIds": ["basic-2014-spells", "free-2024-cleric", "free-2024-spells"],
      "notes": ["Only leveled Cleric spells are included because the artifact exposes level 1–9 charges, not cantrips."]
    },
    {
      "id": "healing-potion-formulas",
      "repository": "cbw29512/healingbox",
      "path": "rules-data.js#POTIONS",
      "status": "verified",
      "verifiedAt": "2026-07-21",
      "sourceIds": ["basic-2014-magic-items", "free-2024-magic-items"],
      "notes": ["Potion formulas are 2d4+2, 4d4+4, 8d4+8, and 10d4+20 in both supported rulesets. The artifact's free-action use is homebrew and documented separately."]
    },
    {
      "id": "cleric-automatic-effects",
      "repository": "cbw29512/healingbox",
      "path": "rules-data.js#EFFECTS;app-v3.js#spellEffect",
      "status": "verified",
      "verifiedAt": "2026-07-21",
      "sourceIds": ["basic-2014-spells", "free-2024-spells"],
      "notes": [
        "All automatic effects currently represented in the tracker were checked for base-slot formula, attack or saving-throw resolution, important successful-save results, and high-impact riders.",
        "Edition differences are explicit for Inflict Wounds, Prayer of Healing, Spiritual Weapon, Spirit Guardians, Flame Strike, Blade Barrier, Heal, Fire Storm, Sunburst, and Mass Heal.",
        "The artifact forbids upcasting, so automatic calculations intentionally represent only the spell's base level.",
        "Spells without an automatic effect entry are recorded as utility/custom resolution and direct the table to resolve the official spell normally."
      ]
    },
    {
      "id": "cleric-artifact-laws",
      "repository": "cbw29512/healingbox",
      "path": "app-v3.js#artifact-law",
      "status": "homebrew",
      "verifiedAt": "2026-07-21",
      "sourceIds": [],
      "notes": ["Free-action activation, immunity to theft/destruction/suppression, and deity-only control are campaign artifact rules, not core D&D rules."]
    },
    {
      "id": "monster-card-samples",
      "repository": "cbw29512/monstercardforge",
      "path": "src/data/monsters.js;src/js/cardEngine.js",
      "status": "verified",
      "verifiedAt": "2026-07-21",
      "sourceIds": ["srd-5-1", "basic-2014-monsters"],
      "notes": [
        "Goblin, Adult Black Dragon, and Lich records contain the complete base SRD stat-block fields used by their published card layouts.",
        "Adult Black Dragon and Lich save DCs, damage values, legendary-action costs, and Lich spell-slot counts are protected by regression tests.",
        "Optional lair actions and regional effects are deliberately excluded until separately sourced and verified.",
        "Every rendered card carries ruleset, exact source, license, and verification metadata."
      ]
    },
    {
      "id": "session-reference-board",
      "repository": "cbw29512/monstercardforge",
      "path": "session-console.html#referenceTab",
      "status": "names-only",
      "verifiedAt": "2026-07-21",
      "sourceIds": ["basic-2014-combat", "basic-2014-conditions", "free-2024-playing", "free-2024-glossary"],
      "notes": ["The board intentionally lists action and condition names plus workflow prompts only and tells the DM to use the selected ruleset's official text for exact adjudication."]
    },
    {
      "id": "magic-item-templates",
      "repository": "cbw29512/monstercardforge",
      "path": "magic-items.js",
      "status": "homebrew",
      "verifiedAt": "2026-07-21",
      "sourceIds": [],
      "notes": ["The builder stores user-created rules. Presets must identify whether they are original DM Forge content, user homebrew, or licensed rules content."]
    },
    {
      "id": "npc-and-loot-generators",
      "repository": "cbw29512/monstercardforge",
      "path": "npc-forge.js;loot-forge.js;session-console.js",
      "status": "homebrew",
      "verifiedAt": "2026-07-21",
      "sourceIds": [],
      "notes": ["Generator tables are original prompts and are not labeled official treasure, NPC, or encounter tables."]
    }
  ]
}
